README.rst
setup.py
django_staticfiles_dotd.egg-info/PKG-INFO
django_staticfiles_dotd.egg-info/SOURCES.txt
django_staticfiles_dotd.egg-info/dependency_links.txt
django_staticfiles_dotd.egg-info/requires.txt
django_staticfiles_dotd.egg-info/top_level.txt
staticfiles_dotd/__init__.py
staticfiles_dotd/app_settings.py
staticfiles_dotd/finders.py
staticfiles_dotd/models.py
staticfiles_dotd/pipeline.py
staticfiles_dotd/utils.py
staticfiles_dotd/views.py