Metadata-Version: 1.0
Name: django-staticfiles-dotd
Version: 2.0.0
Summary: Django staticfiles adaptor to concatentate .d-style directories
Home-page: https://chris-lamb.co.uk/projects/django-staticfiles-dotd
Author: Chris Lamb
Author-email: chris@chris-lamb.co.uk
License: BSD
Platform: UNKNOWN
